LICENSE
MANIFEST.in
README.rst
setup.py
sentry_mailagain/__init__.py
sentry_mailagain/__init__.pyc
sentry_mailagain/forms.py
sentry_mailagain/models.py
sentry_mailagain/plugin.py
sentry_mailagain.egg-info/PKG-INFO
sentry_mailagain.egg-info/SOURCES.txt
sentry_mailagain.egg-info/dependency_links.txt
sentry_mailagain.egg-info/entry_points.txt
sentry_mailagain.egg-info/requires.txt
sentry_mailagain.egg-info/top_level.txt
sentry_mailagain/templates/sentry_mailagain/project_configuration_form.html