Metadata-Version: 1.1
Name: sentry-mailagain
Version: 1.0
Summary: A Sentry plugin that renotifies you of unresolved events
Home-page: https://github.com/simonpercivall/sentry-mailagain
Author: Simon Percivall
Author-email: simon.percivall@trioptima.com
License: BSD
Platform: UNKNOWN
Classifier: Programming Language :: Python
Classifier: Development Status :: 5 - Production/Stable
Classifier: Environment :: Plugins
